functional/__init__.py
functional/execution.py
functional/io.py
functional/lineage.py
functional/pipeline.py
functional/streams.py
functional/test/__init__.py
functional/test/data/test.csv
functional/test/data/test.csv.bz2
functional/test/data/test.csv.gz
functional/test/data/test.csv.xz
functional/test/data/test.jsonl
functional/test/data/test.jsonl.bz2
functional/test/data/test.jsonl.gz
functional/test/data/test.jsonl.xz
functional/test/data/test.txt
functional/test/data/test.txt.bz2
functional/test/data/test.txt.gz
functional/test/data/test.txt.xz
functional/test/data/test_dict.json
functional/test/data/test_dict.json.bz2
functional/test/data/test_dict.json.gz
functional/test/data/test_dict.json.xz
functional/test/data/test_header.csv
functional/test/data/test_list.json
functional/test/data/test_list.json.bz2
functional/test/data/test_list.json.gz
functional/test/data/test_list.json.xz
functional/test/data/test_sqlite3.db
functional/test/data/tmp/.gitkeep
functional/test/test_functional.py
functional/test/test_io.py
functional/test/test_streams.py
functional/test/test_util.py
functional/transformations.py
functional/util.py
pyfunctional-1.4.1.dist-info/LICENSE.txt
pyfunctional-1.4.1.dist-info/WHEEL
pyfunctional-1.4.1.dist-info/METADATA
pyfunctional-1.4.1.dist-info/RECORD
