Metadata-Version: 2.1
Name: pyfunctional
Version: 1.4.1
Summary: Package for creating data pipelines with chain functional programming
Home-page: https://github.com/EntilZha/PyFunctional
License: MIT
Keywords: functional,pipeline,chain
Author: Pedro Rodriguez
Author-email: me@pedro.ai
Maintainer: Pedro Rodriguez
Maintainer-email: me@pedro.ai
Requires-Python: >=3.6.1,<4.0
Classifier: Development Status :: 5 - Production/Stable
Classifier: Intended Audience :: Developers
Classifier: License :: OSI Approved :: MIT License
Classifier: Natural Language :: English
Classifier: Operating System :: OS Independent
Classifier: Programming Language :: Python :: 3
Classifier: Programming Language :: Python :: 3.6
Classifier: Programming Language :: Python :: 3.7
Classifier: Programming Language :: Python :: 3.8
Classifier: Programming Language :: Python :: Implementation :: CPython
Classifier: Programming Language :: Python :: Implementation :: PyPy
Classifier: Topic :: Software Development :: Libraries :: Python Modules
Requires-Dist: dill (>=0.3.2,<0.4.0)
Requires-Dist: pandas[all] (>=1.0.3,<2.0.0)
Requires-Dist: tabulate (<=1.0.0)
Project-URL: Documentation, https://docs.pyfunctional.org/en/master/
Project-URL: Repository, https://github.com/EntilZha/PyFunctional
